[{"itemId":"669440182-5","itemName":"산지직송 사과","category":"과일","price":10000},
{"itemId":"564081720-8","itemName":"싱싱꿀맛 수박","category":"과일","price":13000},
{"itemId":"145926053-8","itemName":"무농약 참외","category":"과일","price":12000},
{"itemId":"009190095-6","itemName":"무농약 오렌지","category":"과일","price":10000},
{"itemId":"262625773-7","itemName":"무농약 자두","category":"과일","price":10900},
{"itemId":"964513734-9","itemName":"새콤달콤 복숭아","category":"과일","price":13000},
{"itemId":"921271789-6","itemName":"싱싱꿀맛 메론","category":"과일","price":24000},
{"itemId":"987482511-1","itemName":"새콤달콤 포도","category":"과일","price":23000},
{"itemId":"119771870-2","itemName":"캘리포니아산 체리","category":"과일","price":21900},
{"itemId":"423198214-7","itemName":"아오리 청사과","category":"과일","price":13400},
{"itemId":"882468065-8","itemName":"중화요리 군만두","category":"레트로트","price":18700},
{"itemId":"088870511-5","itemName":"바삭바삭 군만두","category":"레트로트","price":17400},
{"itemId":"821663327-0","itemName":"냉동 탕수육","category":"레트로트","price":37300},
{"itemId":"609572058-3","itemName":"고르곤졸라 피자","category":"레트로트","price":34000},
{"itemId":"046412642-8","itemName":"얼얼한 짬뽕","category":"레트로트","price":44300},
{"itemId":"903051799-9","itemName":"짜장면","category":"레트로트","price":49500},
{"itemId":"538980740-5","itemName":"마라탕","category":"레트로트","price":23000},
{"itemId":"852436905-1","itemName":"육개장","category":"레트로트","price":25800},
{"itemId":"328424409-3","itemName":"삼겹살 1Kg","category":"정육","price":15800},
{"itemId":"849235646-4","itemName":"소고기","category":"정육","price":14600}]